{
  "id": "c003",
  "title": "临床医生",
  "category": "医学",
  "definition": "在临床一线诊疗患者并持续精进医疗能力。",
  "typicalDay": [
    { "time": "07:30", "task": "晨交班与查房" },
    { "time": "09:30", "task": "门诊接诊与初步诊断" },
    { "time": "13:00", "task": "处理病例与与家属沟通" },
    { "time": "17:00", "task": "学习病例与参加科室讨论" }
  ],
  "coreSkills": {
    "hard": ["临床诊断", "医学知识体系", "影像判读", "病历书写"],
    "soft": ["同理心", "抗压能力", "专注力", "沟通能力"]
  },
  "fit": ["愿意长期学习与积累", "对生命健康有强烈责任感", "能在压力下保持冷静"],
  "unfit": ["难以接受长期培养周期", "抗压能力较弱", "对细节缺乏耐心"],
  "myths": ["当医生就能一劳永逸", "只要学习好就一定轻松"],
  "path": ["规培医师", "主治医师", "副主任医师", "主任医师"],
  "relatedMajors": ["临床医学", "医学影像", "麻醉学", "口腔医学"],
  "learningPath": ["基础医学打底", "临床技能训练", "规范化培训", "专科深耕"]
}
